pypi_github_helper/__init__.py
pypi_github_helper/github_helper.py
pypi_github_helper/manage.py
pypi_github_helper-0.1.5.dist-info/LICENSE
pypi_github_helper-0.1.5.dist-info/METADATA
pypi_github_helper-0.1.5.dist-info/WHEEL
pypi_github_helper-0.1.5.dist-info/entry_points.txt
pypi_github_helper-0.1.5.dist-info/RECORD
